autodistill_gpt_4o/__init__.py
autodistill_gpt_4o/gpt4o_model.py
autodistill_gpt_4o-0.1.5.dist-info/LICENSE
autodistill_gpt_4o-0.1.5.dist-info/METADATA
autodistill_gpt_4o-0.1.5.dist-info/WHEEL
autodistill_gpt_4o-0.1.5.dist-info/top_level.txt
autodistill_gpt_4o-0.1.5.dist-info/RECORD
